MANIFEST.in
setup.py
DistributedLock.egg-info/PKG-INFO
DistributedLock.egg-info/SOURCES.txt
DistributedLock.egg-info/dependency_links.txt
DistributedLock.egg-info/requires.txt
DistributedLock.egg-info/top_level.txt
distributedlock/__init__.py
distributedlock/memcachedlock.py