Metadata-Version: 1.0
Name: DistributedLock
Version: 1.1
Summary: Python Distributed Lock with memcached support
Home-page: https://github.com/snbuback/DistributedLock
Author: Silvano Buback
Author-email: snbuback@gmail.com
License: LICENSE.txt
Platform: UNKNOWN
